[
    {
        "orderId": 111,
        "userId": "user111",
        "userName": "userName1",
        "sellerIds": [
            1,
            2
        ],
        "products": [
            {
                "name": "product1",
                "quantity": 5
            },
            {
                "name": "product2",
                "quantity": 4
            }
        ],
        "totalAmount": 100.00,
        "status": "Shipped",
        "shippingAddress": "456 User Avenue, City, Country",
        "date": "1/1/2025"
    },
    {
        "orderId": 222,
        "userId": "user222",
        "userName": "userName2",
        "sellerIds": [
            2,
            3
        ],
        "products": [
            {
                "name": "product3",
                "quantity": 5
            },
            {
                "name": "product4",
                "quantity": 4
            }
        ],
        "totalAmount": 200.00,
        "status": "Shipped",
        "shippingAddress": "456 User Avenue, City, Country",
        "date": "1/1/2025"
    }
]